fibonacci_calculators/__init__.py
fibonacci_calculators/calculators.py
fibonacci_calculators/fibonacci_calculators.py
fibonacci_calculators-0.0.2.dist-info/LICENSE
fibonacci_calculators-0.0.2.dist-info/METADATA
fibonacci_calculators-0.0.2.dist-info/WHEEL
fibonacci_calculators-0.0.2.dist-info/top_level.txt
fibonacci_calculators-0.0.2.dist-info/RECORD
