Metadata-Version: 2.1
Name: fibonacci-calculators
Version: 0.0.2
Summary: A package to calculate fibonacci number
Home-page: https://github.com/leon0707/fibonacci-calculators
Author: Leon Feng
Author-email: leonlibinfeng@gmail.com
License: UNKNOWN
Platform: UNKNOWN
Classifier: Programming Language :: Python :: 3
Classifier: License :: OSI Approved :: MIT License
Classifier: Operating System :: OS Independent
Requires-Python: >= 2.7, >=3.6
